tvslr/__init__.py
tvslr/__main__.py
tvslr/tvslr.py
tvslr-2.0.0.dist-info/LICENSE
tvslr-2.0.0.dist-info/METADATA
tvslr-2.0.0.dist-info/WHEEL
tvslr-2.0.0.dist-info/entry_points.txt
tvslr-2.0.0.dist-info/top_level.txt
tvslr-2.0.0.dist-info/RECORD
