Metadata-Version: 2.1
Name: tvslr
Version: 2.0.0
Summary: time varying SLR using OLS estimates
Author-email: Arka <arkaprava.mail@gmail.com>
License: MIT License        
Project-URL: Homepage, https://github.com/arka816/tv-slr
Project-URL: repository, https://github.com/arka816/tv-slr
Keywords: regression,time-varying,ols,python
Classifier: License :: OSI Approved :: MIT License
Classifier: Programming Language :: Python
Classifier: Programming Language :: Python :: 3
Requires-Python: >=3.8
License-File: LICENSE
Requires-Dist: numpy
Requires-Dist: pandas
